[{"in_time": {"now_cap_percent": "100 %", "height": "242.25", "capacity": "21,270.96", "time": "2005-11-13(0時)"}, "name": "石門水庫", "daily": {"capacity": "20,898.00", "end_time": "迄:2005-11-14(0時)", "nuclear": "--", "diff": "--", "start_time": "起:2005-11-13(0時)", "in_water": "169.59", "rain": "0.30", "out_water": "177.38"}}, {"in_time": {"now_cap_percent": "99.06 %", "height": "82.83", "capacity": "820.18", "time": "2005-11-13(0時)"}, "name": "新山水庫", "daily": {"capacity": "828.00", "end_time": "迄:2005-11-14(0時)", "nuclear": "--", "diff": "--", "start_time": "起:2005-11-13(0時)", "in_water": "0.00", "rain": "0.00", "out_water": "2.30"}}, {"in_time": {"now_cap_percent": "79.47 %", "height": "161.61", "capacity": "26,719.80", "time": "2005-11-13(0時)"}, "name": "翡翠水庫", "daily": {"capacity": "33,621.65", "end_time": "迄:2005-11-14(0時)", "nuclear": "--", "diff": "--", "start_time": "起:2005-11-13(0時)", "in_water": "170.61", "rain": "25.00", "out_water": "162.31"}}, {"in_time": {"now_cap_percent": "95.48 %", "height": "141.22", "capacity": "510.80", "time": "2005-11-13(0時)"}, "name": "寶山水庫", "daily": {"capacity": "535.00", "end_time": "迄:2005-11-14(0時)", "nuclear": "--", "diff": "--", "start_time": "起:2005-11-13(0時)", "in_water": "9.57", "rain": "0.00", "out_water": "1.97"}}, {"in_time": {"now_cap_percent": "--", "height": "--", "capacity": "--", "time": "--"}, "name": "寶山第二水庫", "daily": {"capacity": "--", "end_time": "迄:--", "nuclear": "--", "diff": "--", "start_time": "起:--", "in_water": "--", "rain": "--", "out_water": "--"}}, {"in_time": {"now_cap_percent": "80.82 %", "height": "82.10", "capacity": "2,270.70", "time": "2005-11-13(0時)"}, "name": "永和山水庫", "daily": {"capacity": "2,809.58", "end_time": "迄:2005-11-14(0時)", "nuclear": "--", "diff": "--", "start_time": "起:2005-11-13(0時)", "in_water": "7.10", "rain": "0.00", "out_water": "22.40"}}, {"in_time": {"now_cap_percent": "68.17 %", "height": "57.75", "capacity": "848.52", "time": "2005-11-13(0時)"}, "name": "明德水庫", "daily": {"capacity": "1,244.76", "end_time": "迄:2005-11-14(0時)", "nuclear": "--", "diff": "--", "start_time": "起:2005-11-13(0時)", "in_water": "4.85", "rain": "0.00", "out_water": "16.08"}}, {"in_time": {"now_cap_percent": "97.2 %", "height": "298.30", "capacity": "11,238.60", "time": "2005-11-13(0時)"}, "name": "鯉魚潭水庫", "daily": {"capacity": "11,562.00", "end_time": "迄:2005-11-14(0時)", "nuclear": "--", "diff": "--", "start_time": "起:2005-11-13(0時)", "in_water": "105.49", "rain": "0.00", "out_water": "118.28"}}, {"in_time": {"now_cap_percent": "--", "height": "1,399.65", "capacity": "13,732.12", "time": "2005-11-13(0時)"}, "name": "德基水庫", "daily": {"capacity": "--", "end_time": "迄:2005-11-14(0時)", "nuclear": "--", "diff": "--", "start_time": "起:2005-11-13(0時)", "in_water": "126.49", "rain": "0.00", "out_water": "0.00"}}, {"in_time": {"now_cap_percent": "62.91 %", "height": "273.96", "capacity": "119.60", "time": "2005-11-13(0時)"}, "name": "石岡壩", "daily": {"capacity": "190.12", "end_time": "迄:2005-11-14(0時)", "nuclear": "--", "diff": "--", "start_time": "起:2005-11-13(0時)", "in_water": "144.30", "rain": "0.00", "out_water": "156.10"}}, {"in_time": {"now_cap_percent": "--", "height": "--", "capacity": "--", "time": "--"}, "name": "霧社水庫", "daily": {"capacity": "--", "end_time": "迄:--", "nuclear": "--", "diff": "--", "start_time": "起:--", "in_water": "--", "rain": "--", "out_water": "--"}}, {"in_time": {"now_cap_percent": "--", "height": "--", "capacity": "--", "time": "--"}, "name": "日月潭水庫", "daily": {"capacity": "--", "end_time": "迄:--", "nuclear": "--", "diff": "--", "start_time": "起:--", "in_water": "--", "rain": "--", "out_water": "--"}}, {"in_time": {"now_cap_percent": "87.86 %", "height": "103.92", "capacity": "2,267.38", "time": "2005-11-13(0時)"}, "name": "仁義潭水庫", "daily": {"capacity": "2,580.61", "end_time": "迄:2005-11-14(0時)", "nuclear": "--", "diff": "--", "start_time": "起:2005-11-13(0時)", "in_water": "4.01", "rain": "0.00", "out_water": "9.00"}}, {"in_time": {"now_cap_percent": "88.63 %", "height": "74.28", "capacity": "820.44", "time": "2005-11-13(0時)"}, "name": "蘭潭水庫", "daily": {"capacity": "925.73", "end_time": "迄:2005-11-14(0時)", "nuclear": "--", "diff": "--", "start_time": "起:2005-11-13(0時)", "in_water": "10.32", "rain": "0.00", "out_water": "4.46"}}, {"in_time": {"now_cap_percent": "61.99 %", "height": "54.30", "capacity": "5,192.00", "time": "2005-11-13(0時)"}, "name": "烏山頭水庫", "daily": {"capacity": "8,375.00", "end_time": "迄:2005-11-14(0時)", "nuclear": "--", "diff": "--", "start_time": "起:2005-11-13(0時)", "in_water": "405.80", "rain": "0.00", "out_water": "383.00"}}, {"in_time": {"now_cap_percent": "99.1 %", "height": "219.82", "capacity": "48,717.00", "time": "2005-11-13(0時)"}, "name": "曾文水庫", "daily": {"capacity": "49,159.00", "end_time": "迄:2005-11-14(0時)", "nuclear": "--", "diff": "--", "start_time": "起:2005-11-13(0時)", "in_water": "56.20", "rain": "2.30", "out_water": "436.80"}}, {"in_time": {"now_cap_percent": "100 %", "height": "178.40", "capacity": "12,455.10", "time": "2005-11-13(0時)"}, "name": "南化水庫", "daily": {"capacity": "10,158.50", "end_time": "迄:2005-11-14(0時)", "nuclear": "--", "diff": "--", "start_time": "起:2005-11-13(0時)", "in_water": "30.80", "rain": "0.00", "out_water": "65.00"}}, {"in_time": {"now_cap_percent": "--", "height": "--", "capacity": "--", "time": "--"}, "name": "阿公店水庫", "daily": {"capacity": "--", "end_time": "迄:--", "nuclear": "--", "diff": "--", "start_time": "起:--", "in_water": "--", "rain": "--", "out_water": "--"}}, {"in_time": {"now_cap_percent": "--", "height": "--", "capacity": "--", "time": "--"}, "name": "阿公店水庫(洩洪至二仁溪)", "daily": {"capacity": "--", "end_time": "迄:--", "nuclear": "--", "diff": "--", "start_time": "起:--", "in_water": "--", "rain": "--", "out_water": "--"}}, {"in_time": {"now_cap_percent": "69.66 %", "height": "133.82", "capacity": "1,945.71", "time": "2005-11-13(0時)"}, "name": "牡丹水庫", "daily": {"capacity": "2,793.04", "end_time": "迄:2005-11-14(0時)", "nuclear": "--", "diff": "--", "start_time": "起:2005-11-13(0時)", "in_water": "43.41", "rain": "17.00", "out_water": "8.64"}}, {"in_time": {"now_cap_percent": "59.9 %", "height": "7.39", "capacity": "62.30", "time": "2005-11-13(0時)"}, "name": "成功水庫", "daily": {"capacity": "104.00", "end_time": "迄:2005-11-14(0時)", "nuclear": "--", "diff": "--", "start_time": "起:2005-11-13(0時)", "in_water": "0.00", "rain": "0.00", "out_water": "0.79"}}]