[{"in_time": {"now_cap_percent": "100 %", "height": "244.74", "capacity": "21,729.76", "time": "2007-12-09(23時)"}, "name": "石門水庫", "daily": {"capacity": "20,898.00", "end_time": "迄:2007-12-10(0時)", "nuclear": "--", "diff": "--", "start_time": "起:2007-12-09(0時)", "in_water": "200.43", "rain": "0.20", "out_water": "74.91"}}, {"in_time": {"now_cap_percent": "93.57 %", "height": "81.84", "capacity": "774.80", "time": "2007-12-09(0時)"}, "name": "新山水庫", "daily": {"capacity": "828.00", "end_time": "迄:2007-12-10(0時)", "nuclear": "--", "diff": "--", "start_time": "起:2007-12-09(0時)", "in_water": "2.70", "rain": "2.00", "out_water": "0.00"}}, {"in_time": {"now_cap_percent": "91.7 %", "height": "166.91", "capacity": "30,830.29", "time": "2007-12-09(7時)"}, "name": "翡翠水庫", "daily": {"capacity": "33,621.65", "end_time": "迄:2007-12-10(0時)", "nuclear": "--", "diff": "--", "start_time": "起:2007-12-09(0時)", "in_water": "142.07", "rain": "1.90", "out_water": "454.07"}}, {"in_time": {"now_cap_percent": "92.26 %", "height": "140.95", "capacity": "493.60", "time": "2007-12-09(0時)"}, "name": "寶山水庫", "daily": {"capacity": "535.00", "end_time": "迄:2007-12-10(0時)", "nuclear": "--", "diff": "--", "start_time": "起:2007-12-09(0時)", "in_water": "12.30", "rain": "0.00", "out_water": "12.00"}}, {"in_time": {"now_cap_percent": "92.95 %", "height": "148.06", "capacity": "2,913.17", "time": "2007-12-09(0時)"}, "name": "寶山第二水庫", "daily": {"capacity": "3,134.00", "end_time": "迄:2007-12-10(0時)", "nuclear": "--", "diff": "--", "start_time": "起:2007-12-09(0時)", "in_water": "0.03", "rain": "0.00", "out_water": "1.50"}}, {"in_time": {"now_cap_percent": "80.49 %", "height": "82.04", "capacity": "2,261.50", "time": "2007-12-09(0時)"}, "name": "永和山水庫", "daily": {"capacity": "2,809.58", "end_time": "迄:2007-12-10(0時)", "nuclear": "--", "diff": "--", "start_time": "起:2007-12-09(0時)", "in_water": "5.10", "rain": "0.00", "out_water": "18.80"}}, {"in_time": {"now_cap_percent": "76.57 %", "height": "59.14", "capacity": "953.09", "time": "2007-12-09(0時)"}, "name": "明德水庫", "daily": {"capacity": "1,244.76", "end_time": "迄:2007-12-10(0時)", "nuclear": "--", "diff": "--", "start_time": "起:2007-12-09(0時)", "in_water": "3.00", "rain": "0.00", "out_water": "4.41"}}, {"in_time": {"now_cap_percent": "98.2 %", "height": "298.57", "capacity": "11,353.96", "time": "2007-12-09(23時)"}, "name": "鯉魚潭水庫", "daily": {"capacity": "11,562.00", "end_time": "迄:2007-12-10(0時)", "nuclear": "--", "diff": "--", "start_time": "起:2007-12-09(0時)", "in_water": "59.53", "rain": "0.00", "out_water": "87.52"}}, {"in_time": {"now_cap_percent": "--", "height": "1,403.48", "capacity": "15,330.48", "time": "2007-12-09(23時)"}, "name": "德基水庫", "daily": {"capacity": "--", "end_time": "迄:2007-12-10(0時)", "nuclear": "--", "diff": "--", "start_time": "起:2007-12-09(0時)", "in_water": "99.56", "rain": "0.00", "out_water": "334.72"}}, {"in_time": {"now_cap_percent": "26.49 %", "height": "273.51", "capacity": "50.36", "time": "2007-12-09(23時)"}, "name": "石岡壩", "daily": {"capacity": "190.12", "end_time": "迄:2007-12-10(0時)", "nuclear": "--", "diff": "--", "start_time": "起:2007-12-09(0時)", "in_water": "172.50", "rain": "0.00", "out_water": "160.90"}}, {"in_time": {"now_cap_percent": "--", "height": "--", "capacity": "--", "time": "--"}, "name": "霧社水庫", "daily": {"capacity": "--", "end_time": "迄:--", "nuclear": "--", "diff": "--", "start_time": "起:--", "in_water": "--", "rain": "--", "out_water": "--"}}, {"in_time": {"now_cap_percent": "--", "height": "--", "capacity": "--", "time": "--"}, "name": "日月潭水庫", "daily": {"capacity": "--", "end_time": "迄:--", "nuclear": "--", "diff": "--", "start_time": "起:--", "in_water": "--", "rain": "--", "out_water": "--"}}, {"in_time": {"now_cap_percent": "83.64 %", "height": "103.42", "capacity": "2,158.53", "time": "2007-12-09(0時)"}, "name": "仁義潭水庫", "daily": {"capacity": "2,580.61", "end_time": "迄:2007-12-10(0時)", "nuclear": "--", "diff": "--", "start_time": "起:2007-12-09(0時)", "in_water": "0.00", "rain": "0.00", "out_water": "8.87"}}, {"in_time": {"now_cap_percent": "88.39 %", "height": "74.25", "capacity": "818.25", "time": "2007-12-09(0時)"}, "name": "蘭潭水庫", "daily": {"capacity": "925.73", "end_time": "迄:2007-12-10(0時)", "nuclear": "--", "diff": "--", "start_time": "起:2007-12-09(0時)", "in_water": "0.00", "rain": "0.00", "out_water": "6.66"}}, {"in_time": {"now_cap_percent": "89.55 %", "height": "57.16", "capacity": "7,500.00", "time": "2007-12-09(0時)"}, "name": "烏山頭水庫", "daily": {"capacity": "8,375.00", "end_time": "迄:2007-12-10(0時)", "nuclear": "--", "diff": "--", "start_time": "起:2007-12-09(0時)", "in_water": "320.40", "rain": "0.00", "out_water": "168.00"}}, {"in_time": {"now_cap_percent": "100 %", "height": "222.35", "capacity": "50,419.00", "time": "2007-12-09(23時)"}, "name": "曾文水庫", "daily": {"capacity": "49,159.00", "end_time": "迄:2007-12-10(0時)", "nuclear": "--", "diff": "--", "start_time": "起:2007-12-09(0時)", "in_water": "26.20", "rain": "0.00", "out_water": "417.20"}}, {"in_time": {"now_cap_percent": "82.78 %", "height": "169.28", "capacity": "8,409.60", "time": "2007-12-09(23時)"}, "name": "南化水庫", "daily": {"capacity": "10,158.50", "end_time": "迄:2007-12-10(0時)", "nuclear": "--", "diff": "--", "start_time": "起:2007-12-09(0時)", "in_water": "0.30", "rain": "0.00", "out_water": "25.00"}}, {"in_time": {"now_cap_percent": "--", "height": "--", "capacity": "--", "time": "--"}, "name": "阿公店水庫", "daily": {"capacity": "--", "end_time": "迄:--", "nuclear": "--", "diff": "--", "start_time": "起:--", "in_water": "--", "rain": "--", "out_water": "--"}}, {"in_time": {"now_cap_percent": "--", "height": "--", "capacity": "--", "time": "--"}, "name": "阿公店水庫(洩洪至二仁溪)", "daily": {"capacity": "--", "end_time": "迄:--", "nuclear": "--", "diff": "--", "start_time": "起:--", "in_water": "--", "rain": "--", "out_water": "--"}}, {"in_time": {"now_cap_percent": "93.55 %", "height": "139.82", "capacity": "2,612.90", "time": "2007-12-09(23時)"}, "name": "牡丹水庫", "daily": {"capacity": "2,793.04", "end_time": "迄:2007-12-10(0時)", "nuclear": "--", "diff": "--", "start_time": "起:2007-12-09(0時)", "in_water": "16.04", "rain": "0.00", "out_water": "12.10"}}, {"in_time": {"now_cap_percent": "66.63 %", "height": "7.73", "capacity": "69.30", "time": "2007-12-09(0時)"}, "name": "成功水庫", "daily": {"capacity": "104.00", "end_time": "迄:2007-12-10(0時)", "nuclear": "--", "diff": "--", "start_time": "起:2007-12-09(0時)", "in_water": "0.00", "rain": "0.00", "out_water": "0.58"}}]