[{"in_time": {"now_cap_percent": "88.47 %", "height": "240.93", "capacity": "18,488.01", "time": "2007-04-29(0時)"}, "name": "石門水庫", "daily": {"capacity": "20,898.00", "end_time": "迄:2007-04-30(0時)", "nuclear": "--", "diff": "--", "start_time": "起:2007-04-29(0時)", "in_water": "193.97", "rain": "0.60", "out_water": "120.61"}}, {"in_time": {"now_cap_percent": "99.5 %", "height": "82.91", "capacity": "823.86", "time": "2007-04-29(0時)"}, "name": "新山水庫", "daily": {"capacity": "828.00", "end_time": "迄:2007-04-30(0時)", "nuclear": "--", "diff": "--", "start_time": "起:2007-04-29(0時)", "in_water": "5.06", "rain": "0.00", "out_water": "0.00"}}, {"in_time": {"now_cap_percent": "69.75 %", "height": "158.11", "capacity": "23,449.80", "time": "2007-04-29(0時)"}, "name": "翡翠水庫", "daily": {"capacity": "33,621.65", "end_time": "迄:2007-04-30(0時)", "nuclear": "--", "diff": "--", "start_time": "起:2007-04-29(0時)", "in_water": "67.89", "rain": "6.50", "out_water": "162.79"}}, {"in_time": {"now_cap_percent": "96.67 %", "height": "141.32", "capacity": "517.20", "time": "2007-04-29(0時)"}, "name": "寶山水庫", "daily": {"capacity": "535.00", "end_time": "迄:2007-04-30(0時)", "nuclear": "--", "diff": "--", "start_time": "起:2007-04-29(0時)", "in_water": "13.06", "rain": "0.00", "out_water": "12.86"}}, {"in_time": {"now_cap_percent": "61.45 %", "height": "140.51", "capacity": "1,925.90", "time": "2007-04-29(0時)"}, "name": "寶山第二水庫", "daily": {"capacity": "3,134.00", "end_time": "迄:2007-04-30(0時)", "nuclear": "--", "diff": "--", "start_time": "起:2007-04-29(0時)", "in_water": "0.70", "rain": "0.00", "out_water": "0.70"}}, {"in_time": {"now_cap_percent": "91.9 %", "height": "84.12", "capacity": "2,581.90", "time": "2007-04-29(0時)"}, "name": "永和山水庫", "daily": {"capacity": "2,809.58", "end_time": "迄:2007-04-30(0時)", "nuclear": "--", "diff": "--", "start_time": "起:2007-04-29(0時)", "in_water": "18.90", "rain": "0.00", "out_water": "17.20"}}, {"in_time": {"now_cap_percent": "100 %", "height": "60.87", "capacity": "1,304.67", "time": "2007-04-29(0時)"}, "name": "明德水庫", "daily": {"capacity": "1,244.76", "end_time": "迄:2007-04-30(0時)", "nuclear": "--", "diff": "--", "start_time": "起:2007-04-29(0時)", "in_water": "8.89", "rain": "0.00", "out_water": "18.37"}}, {"in_time": {"now_cap_percent": "100 %", "height": "300.03", "capacity": "11,992.60", "time": "2007-04-29(0時)"}, "name": "鯉魚潭水庫", "daily": {"capacity": "11,562.00", "end_time": "迄:2007-04-30(0時)", "nuclear": "--", "diff": "--", "start_time": "起:2007-04-29(0時)", "in_water": "197.25", "rain": "0.00", "out_water": "201.80"}}, {"in_time": {"now_cap_percent": "--", "height": "1,400.56", "capacity": "14,102.04", "time": "2007-04-29(0時)"}, "name": "德基水庫", "daily": {"capacity": "--", "end_time": "迄:2007-04-30(0時)", "nuclear": "--", "diff": "--", "start_time": "起:2007-04-29(0時)", "in_water": "204.87", "rain": "0.00", "out_water": "321.59"}}, {"in_time": {"now_cap_percent": "12.99 %", "height": "272.79", "capacity": "24.70", "time": "2007-04-29(0時)"}, "name": "石岡壩", "daily": {"capacity": "190.12", "end_time": "迄:2007-04-30(0時)", "nuclear": "--", "diff": "--", "start_time": "起:2007-04-29(0時)", "in_water": "712.00", "rain": "0.00", "out_water": "717.40"}}, {"in_time": {"now_cap_percent": "--", "height": "--", "capacity": "--", "time": "--"}, "name": "霧社水庫", "daily": {"capacity": "--", "end_time": "迄:--", "nuclear": "--", "diff": "--", "start_time": "起:--", "in_water": "--", "rain": "--", "out_water": "--"}}, {"in_time": {"now_cap_percent": "--", "height": "--", "capacity": "--", "time": "--"}, "name": "日月潭水庫", "daily": {"capacity": "--", "end_time": "迄:--", "nuclear": "--", "diff": "--", "start_time": "起:--", "in_water": "--", "rain": "--", "out_water": "--"}}, {"in_time": {"now_cap_percent": "26.24 %", "height": "95.73", "capacity": "677.15", "time": "2007-04-29(0時)"}, "name": "仁義潭水庫", "daily": {"capacity": "2,580.61", "end_time": "迄:2007-04-30(0時)", "nuclear": "--", "diff": "--", "start_time": "起:2007-04-29(0時)", "in_water": "1.50", "rain": "0.00", "out_water": "9.10"}}, {"in_time": {"now_cap_percent": "37.06 %", "height": "66.99", "capacity": "343.03", "time": "2007-04-29(0時)"}, "name": "蘭潭水庫", "daily": {"capacity": "925.73", "end_time": "迄:2007-04-30(0時)", "nuclear": "--", "diff": "--", "start_time": "起:2007-04-29(0時)", "in_water": "0.00", "rain": "0.00", "out_water": "6.28"}}, {"in_time": {"now_cap_percent": "69.84 %", "height": "55.15", "capacity": "5,849.00", "time": "2007-04-29(0時)"}, "name": "烏山頭水庫", "daily": {"capacity": "8,375.00", "end_time": "迄:2007-04-30(0時)", "nuclear": "--", "diff": "--", "start_time": "起:2007-04-29(0時)", "in_water": "0.00", "rain": "0.00", "out_water": "211.00"}}, {"in_time": {"now_cap_percent": "18.68 %", "height": "188.95", "capacity": "9,184.00", "time": "2007-04-29(0時)"}, "name": "曾文水庫", "daily": {"capacity": "49,159.00", "end_time": "迄:2007-04-30(0時)", "nuclear": "--", "diff": "--", "start_time": "起:2007-04-29(0時)", "in_water": "31.00", "rain": "0.00", "out_water": "0.00"}}, {"in_time": {"now_cap_percent": "27.17 %", "height": "151.40", "capacity": "2,759.90", "time": "2007-04-29(0時)"}, "name": "南化水庫", "daily": {"capacity": "10,158.50", "end_time": "迄:2007-04-30(0時)", "nuclear": "--", "diff": "--", "start_time": "起:2007-04-29(0時)", "in_water": "5.90", "rain": "0.00", "out_water": "43.90"}}, {"in_time": {"now_cap_percent": "--", "height": "--", "capacity": "--", "time": "--"}, "name": "阿公店水庫", "daily": {"capacity": "--", "end_time": "迄:--", "nuclear": "--", "diff": "--", "start_time": "起:--", "in_water": "--", "rain": "--", "out_water": "--"}}, {"in_time": {"now_cap_percent": "--", "height": "--", "capacity": "--", "time": "--"}, "name": "阿公店水庫(洩洪至二仁溪)", "daily": {"capacity": "--", "end_time": "迄:--", "nuclear": "--", "diff": "--", "start_time": "起:--", "in_water": "--", "rain": "--", "out_water": "--"}}, {"in_time": {"now_cap_percent": "46.13 %", "height": "127.58", "capacity": "1,288.56", "time": "2007-04-29(0時)"}, "name": "牡丹水庫", "daily": {"capacity": "2,793.04", "end_time": "迄:2007-04-30(0時)", "nuclear": "--", "diff": "--", "start_time": "起:2007-04-29(0時)", "in_water": "1.73", "rain": "0.00", "out_water": "9.50"}}, {"in_time": {"now_cap_percent": "23.75 %", "height": "5.10", "capacity": "24.70", "time": "2007-04-29(0時)"}, "name": "成功水庫", "daily": {"capacity": "104.00", "end_time": "迄:2007-04-30(0時)", "nuclear": "--", "diff": "--", "start_time": "起:2007-04-29(0時)", "in_water": "0.00", "rain": "0.00", "out_water": "0.36"}}]