[{"in_time": {"now_cap_percent": "92.47 %", "height": "241.95", "capacity": "19,324.08", "time": "2007-07-24(0時)"}, "name": "石門水庫", "daily": {"capacity": "20,898.00", "end_time": "迄:2007-07-25(0時)", "nuclear": "--", "diff": "--", "start_time": "起:2007-07-24(0時)", "in_water": "229.72", "rain": "0.40", "out_water": "287.11"}}, {"in_time": {"now_cap_percent": "90.31 %", "height": "81.24", "capacity": "747.80", "time": "2007-07-24(0時)"}, "name": "新山水庫", "daily": {"capacity": "828.00", "end_time": "迄:2007-07-25(0時)", "nuclear": "--", "diff": "--", "start_time": "起:2007-07-24(0時)", "in_water": "0.00", "rain": "0.00", "out_water": "10.80"}}, {"in_time": {"now_cap_percent": "73.64 %", "height": "159.75", "capacity": "24,760.60", "time": "2007-07-24(0時)"}, "name": "翡翠水庫", "daily": {"capacity": "33,621.65", "end_time": "迄:2007-07-25(0時)", "nuclear": "--", "diff": "--", "start_time": "起:2007-07-24(0時)", "in_water": "42.12", "rain": "0.00", "out_water": "187.72"}}, {"in_time": {"now_cap_percent": "99.29 %", "height": "141.54", "capacity": "531.20", "time": "2007-07-24(0時)"}, "name": "寶山水庫", "daily": {"capacity": "535.00", "end_time": "迄:2007-07-25(0時)", "nuclear": "--", "diff": "--", "start_time": "起:2007-07-24(0時)", "in_water": "15.65", "rain": "0.00", "out_water": "14.15"}}, {"in_time": {"now_cap_percent": "78.14 %", "height": "144.72", "capacity": "2,449.00", "time": "2007-07-24(0時)"}, "name": "寶山第二水庫", "daily": {"capacity": "3,134.00", "end_time": "迄:2007-07-25(0時)", "nuclear": "--", "diff": "--", "start_time": "起:2007-07-24(0時)", "in_water": "19.20", "rain": "0.00", "out_water": "7.40"}}, {"in_time": {"now_cap_percent": "89.89 %", "height": "83.76", "capacity": "2,525.50", "time": "2007-07-24(0時)"}, "name": "永和山水庫", "daily": {"capacity": "2,809.58", "end_time": "迄:2007-07-25(0時)", "nuclear": "--", "diff": "--", "start_time": "起:2007-07-24(0時)", "in_water": "5.60", "rain": "0.00", "out_water": "21.70"}}, {"in_time": {"now_cap_percent": "82.91 %", "height": "59.72", "capacity": "1,032.08", "time": "2007-07-24(0時)"}, "name": "明德水庫", "daily": {"capacity": "1,244.76", "end_time": "迄:2007-07-25(0時)", "nuclear": "--", "diff": "--", "start_time": "起:2007-07-24(0時)", "in_water": "3.27", "rain": "0.00", "out_water": "19.72"}}, {"in_time": {"now_cap_percent": "100 %", "height": "299.75", "capacity": "11,868.61", "time": "2007-07-24(0時)"}, "name": "鯉魚潭水庫", "daily": {"capacity": "11,562.00", "end_time": "迄:2007-07-25(0時)", "nuclear": "--", "diff": "--", "start_time": "起:2007-07-24(0時)", "in_water": "126.06", "rain": "0.00", "out_water": "148.17"}}, {"in_time": {"now_cap_percent": "--", "height": "1,393.45", "capacity": "11,399.00", "time": "2007-07-24(0時)"}, "name": "德基水庫", "daily": {"capacity": "--", "end_time": "迄:2007-07-25(0時)", "nuclear": "--", "diff": "--", "start_time": "起:2007-07-24(0時)", "in_water": "127.06", "rain": "0.00", "out_water": "252.40"}}, {"in_time": {"now_cap_percent": "15.83 %", "height": "272.98", "capacity": "30.10", "time": "2007-07-24(0時)"}, "name": "石岡壩", "daily": {"capacity": "190.12", "end_time": "迄:2007-07-25(0時)", "nuclear": "--", "diff": "--", "start_time": "起:2007-07-24(0時)", "in_water": "455.70", "rain": "0.00", "out_water": "454.40"}}, {"in_time": {"now_cap_percent": "--", "height": "--", "capacity": "--", "time": "--"}, "name": "霧社水庫", "daily": {"capacity": "--", "end_time": "迄:--", "nuclear": "--", "diff": "--", "start_time": "起:--", "in_water": "--", "rain": "--", "out_water": "--"}}, {"in_time": {"now_cap_percent": "--", "height": "--", "capacity": "--", "time": "--"}, "name": "日月潭水庫", "daily": {"capacity": "--", "end_time": "迄:--", "nuclear": "--", "diff": "--", "start_time": "起:--", "in_water": "--", "rain": "--", "out_water": "--"}}, {"in_time": {"now_cap_percent": "94.95 %", "height": "104.75", "capacity": "2,450.36", "time": "2007-07-24(0時)"}, "name": "仁義潭水庫", "daily": {"capacity": "2,580.61", "end_time": "迄:2007-07-25(0時)", "nuclear": "--", "diff": "--", "start_time": "起:2007-07-24(0時)", "in_water": "22.84", "rain": "0.00", "out_water": "22.84"}}, {"in_time": {"now_cap_percent": "96.62 %", "height": "75.28", "capacity": "894.46", "time": "2007-07-24(0時)"}, "name": "蘭潭水庫", "daily": {"capacity": "925.73", "end_time": "迄:2007-07-25(0時)", "nuclear": "--", "diff": "--", "start_time": "起:2007-07-24(0時)", "in_water": "11.69", "rain": "0.00", "out_water": "11.69"}}, {"in_time": {"now_cap_percent": "72.05 %", "height": "55.38", "capacity": "6,034.00", "time": "2007-07-24(0時)"}, "name": "烏山頭水庫", "daily": {"capacity": "8,375.00", "end_time": "迄:2007-07-25(0時)", "nuclear": "--", "diff": "--", "start_time": "起:2007-07-24(0時)", "in_water": "58.80", "rain": "0.00", "out_water": "493.00"}}, {"in_time": {"now_cap_percent": "34.32 %", "height": "197.47", "capacity": "16,869.00", "time": "2007-07-24(0時)"}, "name": "曾文水庫", "daily": {"capacity": "49,159.00", "end_time": "迄:2007-07-25(0時)", "nuclear": "--", "diff": "--", "start_time": "起:2007-07-24(0時)", "in_water": "80.00", "rain": "1.00", "out_water": "59.00"}}, {"in_time": {"now_cap_percent": "85.72 %", "height": "170.02", "capacity": "8,707.60", "time": "2007-07-24(0時)"}, "name": "南化水庫", "daily": {"capacity": "10,158.50", "end_time": "迄:2007-07-25(0時)", "nuclear": "--", "diff": "--", "start_time": "起:2007-07-24(0時)", "in_water": "37.30", "rain": "0.00", "out_water": "74.40"}}, {"in_time": {"now_cap_percent": "3.11 %", "height": "27.19", "capacity": "52.55", "time": "2007-07-24(0時)"}, "name": "阿公店水庫", "daily": {"capacity": "1,687.00", "end_time": "迄:2007-07-25(0時)", "nuclear": "--", "diff": "--", "start_time": "起:2007-07-24(0時)", "in_water": "38.49", "rain": "0.00", "out_water": "27.15"}}, {"in_time": {"now_cap_percent": "--", "height": "--", "capacity": "--", "time": "--"}, "name": "阿公店水庫(洩洪至二仁溪)", "daily": {"capacity": "--", "end_time": "迄:--", "nuclear": "--", "diff": "--", "start_time": "起:--", "in_water": "--", "rain": "--", "out_water": "--"}}, {"in_time": {"now_cap_percent": "27.14 %", "height": "120.73", "capacity": "757.94", "time": "2007-07-24(0時)"}, "name": "牡丹水庫", "daily": {"capacity": "2,793.04", "end_time": "迄:2007-07-25(0時)", "nuclear": "--", "diff": "--", "start_time": "起:2007-07-24(0時)", "in_water": "2.47", "rain": "0.00", "out_water": "8.64"}}, {"in_time": {"now_cap_percent": "5.48 %", "height": "3.20", "capacity": "5.70", "time": "2007-07-24(0時)"}, "name": "成功水庫", "daily": {"capacity": "104.00", "end_time": "迄:2007-07-25(0時)", "nuclear": "--", "diff": "--", "start_time": "起:2007-07-24(0時)", "in_water": "0.00", "rain": "0.00", "out_water": "0.00"}}]