[{"in_time": {"now_cap_percent": "88.33 %", "height": "242.11", "capacity": "18,495.89", "time": "2014-07-25(23時)"}, "name": "石門水庫", "daily": {"capacity": "20,940.10", "end_time": "迄:2014-07-26(0時)", "nuclear": "--", "diff": "-0.85", "start_time": "起:2014-07-25(0時)", "in_water": "1,580.08", "rain": "28.90", "out_water": "2,277.07"}}, {"in_time": {"now_cap_percent": "75.48 %", "height": "81.43", "capacity": "756.35", "time": "2014-07-25(8時)"}, "name": "新山水庫", "daily": {"capacity": "1,002.00", "end_time": "迄:2014-07-26(0時)", "nuclear": "--", "diff": "--", "start_time": "起:2014-07-25(0時)", "in_water": "5.40", "rain": "4.50", "out_water": "0.00"}}, {"in_time": {"now_cap_percent": "81.18 %", "height": "162.90", "capacity": "27,234.99", "time": "2014-07-25(23時)"}, "name": "翡翠水庫", "daily": {"capacity": "33,550.50", "end_time": "迄:2014-07-26(0時)", "nuclear": "--", "diff": "-0.15", "start_time": "起:2014-07-25(0時)", "in_water": "396.92", "rain": "8.40", "out_water": "675.82"}}, {"in_time": {"now_cap_percent": "90.2 %", "height": "140.77", "capacity": "485.29", "time": "2014-07-25(7時)"}, "name": "寶山水庫", "daily": {"capacity": "538.00", "end_time": "迄:2014-07-26(0時)", "nuclear": "--", "diff": "--", "start_time": "起:2014-07-25(0時)", "in_water": "23.16", "rain": "81.00", "out_water": "8.89"}}, {"in_time": {"now_cap_percent": "98.09 %", "height": "149.60", "capacity": "3,087.10", "time": "2014-07-25(23時)"}, "name": "寶山第二水庫", "daily": {"capacity": "3,147.18", "end_time": "迄:2014-07-26(0時)", "nuclear": "--", "diff": "0.09", "start_time": "起:2014-07-25(0時)", "in_water": "31.22", "rain": "116.00", "out_water": "18.58"}}, {"in_time": {"now_cap_percent": "93 %", "height": "83.85", "capacity": "2,612.86", "time": "2014-07-25(23時)"}, "name": "永和山水庫", "daily": {"capacity": "2,809.58", "end_time": "迄:2014-07-26(8時)", "nuclear": "--", "diff": "--", "start_time": "起:2014-07-25(8時)", "in_water": "20.20", "rain": "9.00", "out_water": "18.40"}}, {"in_time": {"now_cap_percent": "72.93 %", "height": "58.61", "capacity": "930.53", "time": "2014-07-25(7時)"}, "name": "明德水庫", "daily": {"capacity": "1,276.00", "end_time": "迄:2014-07-26(0時)", "nuclear": "--", "diff": "--", "start_time": "起:2014-07-25(0時)", "in_water": "12.72", "rain": "18.50", "out_water": "19.49"}}, {"in_time": {"now_cap_percent": "93.38 %", "height": "298.21", "capacity": "10,782.74", "time": "2014-07-25(21時)"}, "name": "鯉魚潭水庫", "daily": {"capacity": "11,546.97", "end_time": "迄:2014-07-26(0時)", "nuclear": "--", "diff": "--", "start_time": "起:2014-07-25(0時)", "in_water": "37.41", "rain": "8.62", "out_water": "114.05"}}, {"in_time": {"now_cap_percent": "94.89 %", "height": "1,406.00", "capacity": "14,233.89", "time": "2014-07-25(8時)"}, "name": "德基水庫", "daily": {"capacity": "15,000.00", "end_time": "迄:2014-07-26(8時)", "nuclear": "--", "diff": "--", "start_time": "起:2014-07-25(8時)", "in_water": "853.96", "rain": "2.00", "out_water": "606.75"}}, {"in_time": {"now_cap_percent": "30.08 %", "height": "272.46", "capacity": "34.08", "time": "2014-07-25(21時)"}, "name": "石岡壩", "daily": {"capacity": "113.30", "end_time": "迄:2014-07-26(0時)", "nuclear": "--", "diff": "--", "start_time": "起:2014-07-25(0時)", "in_water": "2,138.00", "rain": "25.00", "out_water": "2,133.40"}}, {"in_time": {"now_cap_percent": "86.41 %", "height": "1,002.63", "capacity": "3,777.88", "time": "2014-07-25(7時)"}, "name": "霧社水庫", "daily": {"capacity": "4,372.08", "end_time": "迄:2014-07-26(0時)", "nuclear": "--", "diff": "--", "start_time": "起:2014-07-25(0時)", "in_water": "406.08", "rain": "4.00", "out_water": "327.31"}}, {"in_time": {"now_cap_percent": "91.34 %", "height": "747.09", "capacity": "11,988.23", "time": "2014-07-25(7時)"}, "name": "日月潭水庫", "daily": {"capacity": "13,124.63", "end_time": "迄:2014-07-26(0時)", "nuclear": "--", "diff": "--", "start_time": "起:2014-07-25(0時)", "in_water": "348.62", "rain": "34.00", "out_water": "296.70"}}, {"in_time": {"now_cap_percent": "83.08 %", "height": "102.99", "capacity": "2,143.58", "time": "2014-07-25(7時)"}, "name": "仁義潭水庫", "daily": {"capacity": "2,580.00", "end_time": "迄:2014-07-26(0時)", "nuclear": "--", "diff": "--", "start_time": "起:2014-07-25(0時)", "in_water": "121.28", "rain": "3.00", "out_water": "17.56"}}, {"in_time": {"now_cap_percent": "95.7 %", "height": "74.87", "capacity": "884.01", "time": "2014-07-25(7時)"}, "name": "蘭潭水庫", "daily": {"capacity": "923.73", "end_time": "迄:2014-07-26(0時)", "nuclear": "--", "diff": "--", "start_time": "起:2014-07-25(0時)", "in_water": "1.25", "rain": "2.00", "out_water": "8.97"}}, {"in_time": {"now_cap_percent": "73.49 %", "height": "55.84", "capacity": "5,866.00", "time": "2014-07-25(7時)"}, "name": "烏山頭水庫", "daily": {"capacity": "7,982.00", "end_time": "迄:2014-07-26(7時)", "nuclear": "--", "diff": "--", "start_time": "起:2014-07-25(7時)", "in_water": "17.60", "rain": "3.80", "out_water": "299.60"}}, {"in_time": {"now_cap_percent": "59.2 %", "height": "215.02", "capacity": "28,018.00", "time": "2014-07-25(17時)"}, "name": "曾文水庫", "daily": {"capacity": "47,330.00", "end_time": "迄:2014-07-26(0時)", "nuclear": "--", "diff": "--", "start_time": "起:2014-07-25(0時)", "in_water": "958.00", "rain": "6.30", "out_water": "0.00"}}, {"in_time": {"now_cap_percent": "81.09 %", "height": "176.11", "capacity": "7,940.70", "time": "2014-07-25(7時)"}, "name": "南化水庫", "daily": {"capacity": "9,793.00", "end_time": "迄:2014-07-26(0時)", "nuclear": "--", "diff": "--", "start_time": "起:2014-07-25(0時)", "in_water": "130.90", "rain": "10.20", "out_water": "107.90"}}, {"in_time": {"now_cap_percent": "6.05 %", "height": "29.62", "capacity": "100.96", "time": "2014-07-25(17時)"}, "name": "阿公店水庫", "daily": {"capacity": "1,669.00", "end_time": "迄:2014-07-26(0時)", "nuclear": "--", "diff": "--", "start_time": "起:2014-07-25(0時)", "in_water": "13.88", "rain": "18.50", "out_water": "25.66"}}, {"in_time": {"now_cap_percent": "--", "height": "--", "capacity": "--", "time": "--"}, "name": "阿公店水庫(洩洪至二仁溪)", "daily": {"capacity": "--", "end_time": "迄:--", "nuclear": "--", "diff": "--", "start_time": "起:--", "in_water": "--", "rain": "--", "out_water": "--"}}, {"in_time": {"now_cap_percent": "55.85 %", "height": "131.83", "capacity": "1,496.10", "time": "2014-07-25(17時)"}, "name": "牡丹水庫", "daily": {"capacity": "2,679.00", "end_time": "迄:2014-07-26(0時)", "nuclear": "--", "diff": "--", "start_time": "起:2014-07-25(0時)", "in_water": "70.95", "rain": "35.50", "out_water": "11.23"}}, {"in_time": {"now_cap_percent": "43.3 %", "height": "6.90", "capacity": "52.40", "time": "2014-07-25(7時)"}, "name": "成功水庫", "daily": {"capacity": "121.01", "end_time": "迄:2014-07-26(0時)", "nuclear": "--", "diff": "0.20", "start_time": "起:2014-07-25(0時)", "in_water": "3.80", "rain": "5.60", "out_water": "0.46"}}]