[{"in_time": {"now_cap_percent": "51.47 %", "height": "226.70", "capacity": "10,756.95", "time": "2004-04-08(0時)"}, "name": "石門水庫", "daily": {"capacity": "20,898.00", "end_time": "迄:2004-04-09(0時)", "nuclear": "--", "diff": "--", "start_time": "起:2004-04-08(0時)", "in_water": "233.54", "rain": "0.00", "out_water": "91.50"}}, {"in_time": {"now_cap_percent": "99.94 %", "height": "82.99", "capacity": "827.54", "time": "2004-04-08(0時)"}, "name": "新山水庫", "daily": {"capacity": "828.00", "end_time": "迄:2004-04-09(0時)", "nuclear": "--", "diff": "--", "start_time": "起:2004-04-08(0時)", "in_water": "3.04", "rain": "23.00", "out_water": "3.50"}}, {"in_time": {"now_cap_percent": "83.63 %", "height": "163.28", "capacity": "28,118.30", "time": "2004-04-08(0時)"}, "name": "翡翠水庫", "daily": {"capacity": "33,621.65", "end_time": "迄:2004-04-09(0時)", "nuclear": "--", "diff": "--", "start_time": "起:2004-04-08(0時)", "in_water": "126.70", "rain": "2.70", "out_water": "0.00"}}, {"in_time": {"now_cap_percent": "99.89 %", "height": "141.59", "capacity": "534.40", "time": "2004-04-08(0時)"}, "name": "寶山水庫", "daily": {"capacity": "535.00", "end_time": "迄:2004-04-09(0時)", "nuclear": "--", "diff": "--", "start_time": "起:2004-04-08(0時)", "in_water": "10.30", "rain": "35.00", "out_water": "9.00"}}, {"in_time": {"now_cap_percent": "--", "height": "--", "capacity": "--", "time": "--"}, "name": "寶山第二水庫", "daily": {"capacity": "--", "end_time": "迄:--", "nuclear": "--", "diff": "--", "start_time": "起:--", "in_water": "--", "rain": "--", "out_water": "--"}}, {"in_time": {"now_cap_percent": "69.79 %", "height": "79.88", "capacity": "1,960.80", "time": "2004-04-08(0時)"}, "name": "永和山水庫", "daily": {"capacity": "2,809.58", "end_time": "迄:2004-04-09(0時)", "nuclear": "--", "diff": "--", "start_time": "起:2004-04-08(0時)", "in_water": "66.90", "rain": "36.00", "out_water": "14.60"}}, {"in_time": {"now_cap_percent": "100 %", "height": "60.85", "capacity": "1,301.51", "time": "2004-04-08(0時)"}, "name": "明德水庫", "daily": {"capacity": "1,244.76", "end_time": "迄:2004-04-09(0時)", "nuclear": "--", "diff": "--", "start_time": "起:2004-04-08(0時)", "in_water": "31.14", "rain": "39.90", "out_water": "26.40"}}, {"in_time": {"now_cap_percent": "75.34 %", "height": "291.76", "capacity": "8,711.17", "time": "2004-04-08(0時)"}, "name": "鯉魚潭水庫", "daily": {"capacity": "11,562.00", "end_time": "迄:2004-04-09(0時)", "nuclear": "--", "diff": "--", "start_time": "起:2004-04-08(0時)", "in_water": "225.07", "rain": "0.00", "out_water": "30.59"}}, {"in_time": {"now_cap_percent": "--", "height": "1,391.51", "capacity": "10,411.87", "time": "2004-04-08(0時)"}, "name": "德基水庫", "daily": {"capacity": "--", "end_time": "迄:2004-04-09(0時)", "nuclear": "--", "diff": "--", "start_time": "起:2004-04-08(0時)", "in_water": "242.96", "rain": "11.00", "out_water": "104.10"}}, {"in_time": {"now_cap_percent": "63.91 %", "height": "272.90", "capacity": "121.50", "time": "2004-04-08(0時)"}, "name": "石岡壩", "daily": {"capacity": "190.12", "end_time": "迄:2004-04-09(0時)", "nuclear": "--", "diff": "--", "start_time": "起:2004-04-08(0時)", "in_water": "219.40", "rain": "0.00", "out_water": "226.40"}}, {"in_time": {"now_cap_percent": "--", "height": "--", "capacity": "--", "time": "--"}, "name": "霧社水庫", "daily": {"capacity": "--", "end_time": "迄:--", "nuclear": "--", "diff": "--", "start_time": "起:--", "in_water": "--", "rain": "--", "out_water": "--"}}, {"in_time": {"now_cap_percent": "--", "height": "--", "capacity": "--", "time": "--"}, "name": "日月潭水庫", "daily": {"capacity": "--", "end_time": "迄:--", "nuclear": "--", "diff": "--", "start_time": "起:--", "in_water": "--", "rain": "--", "out_water": "--"}}, {"in_time": {"now_cap_percent": "32.09 %", "height": "96.31", "capacity": "828.15", "time": "2004-04-08(0時)"}, "name": "仁義潭水庫", "daily": {"capacity": "2,580.61", "end_time": "迄:2004-04-09(0時)", "nuclear": "--", "diff": "--", "start_time": "起:2004-04-08(0時)", "in_water": "2.62", "rain": "3.50", "out_water": "8.76"}}, {"in_time": {"now_cap_percent": "40.36 %", "height": "67.50", "capacity": "373.62", "time": "2004-04-08(0時)"}, "name": "蘭潭水庫", "daily": {"capacity": "925.73", "end_time": "迄:2004-04-09(0時)", "nuclear": "--", "diff": "--", "start_time": "起:2004-04-08(0時)", "in_water": "3.93", "rain": "7.00", "out_water": "3.75"}}, {"in_time": {"now_cap_percent": "11.41 %", "height": "44.87", "capacity": "956.00", "time": "2004-04-08(0時)"}, "name": "烏山頭水庫", "daily": {"capacity": "8,375.00", "end_time": "迄:2004-04-09(0時)", "nuclear": "--", "diff": "--", "start_time": "起:2004-04-08(0時)", "in_water": "0.00", "rain": "5.40", "out_water": "43.00"}}, {"in_time": {"now_cap_percent": "1.06 %", "height": "172.21", "capacity": "520.00", "time": "2004-04-08(0時)"}, "name": "曾文水庫", "daily": {"capacity": "49,159.00", "end_time": "迄:2004-04-09(0時)", "nuclear": "--", "diff": "--", "start_time": "起:2004-04-08(0時)", "in_water": "26.00", "rain": "2.90", "out_water": "0.00"}}, {"in_time": {"now_cap_percent": "65.38 %", "height": "163.52", "capacity": "6,641.50", "time": "2004-04-08(0時)"}, "name": "南化水庫", "daily": {"capacity": "10,158.50", "end_time": "迄:2004-04-09(0時)", "nuclear": "--", "diff": "--", "start_time": "起:2004-04-08(0時)", "in_water": "0.60", "rain": "0.00", "out_water": "64.40"}}, {"in_time": {"now_cap_percent": "--", "height": "--", "capacity": "--", "time": "--"}, "name": "阿公店水庫", "daily": {"capacity": "--", "end_time": "迄:--", "nuclear": "--", "diff": "--", "start_time": "起:--", "in_water": "--", "rain": "--", "out_water": "--"}}, {"in_time": {"now_cap_percent": "--", "height": "--", "capacity": "--", "time": "--"}, "name": "阿公店水庫(洩洪至二仁溪)", "daily": {"capacity": "--", "end_time": "迄:--", "nuclear": "--", "diff": "--", "start_time": "起:--", "in_water": "--", "rain": "--", "out_water": "--"}}, {"in_time": {"now_cap_percent": "58.11 %", "height": "130.54", "capacity": "1,623.06", "time": "2004-04-08(0時)"}, "name": "牡丹水庫", "daily": {"capacity": "2,793.04", "end_time": "迄:2004-04-09(0時)", "nuclear": "--", "diff": "--", "start_time": "起:2004-04-08(0時)", "in_water": "2.58", "rain": "1.00", "out_water": "12.10"}}, {"in_time": {"now_cap_percent": "--", "height": "0.00", "capacity": "0.00", "time": "2004-04-08(0時)"}, "name": "成功水庫", "daily": {"capacity": "104.00", "end_time": "迄:2004-04-09(0時)", "nuclear": "--", "diff": "--", "start_time": "起:2004-04-08(0時)", "in_water": "0.00", "rain": "0.00", "out_water": "0.00"}}]