[{"in_time": {"now_cap_percent": "21.04 %", "height": "216.96", "capacity": "4,397.98", "time": "2011-05-11(23時)"}, "name": "石門水庫", "daily": {"capacity": "20,898.00", "end_time": "迄:2011-05-12(0時)", "nuclear": "--", "diff": "--", "start_time": "起:2011-05-11(0時)", "in_water": "38.53", "rain": "0.00", "out_water": "254.97"}}, {"in_time": {"now_cap_percent": "95.39 %", "height": "82.17", "capacity": "789.82", "time": "2011-05-11(8時)"}, "name": "新山水庫", "daily": {"capacity": "828.00", "end_time": "迄:2011-05-12(8時)", "nuclear": "--", "diff": "--", "start_time": "起:2011-05-11(8時)", "in_water": "0.00", "rain": "0.00", "out_water": "6.90"}}, {"in_time": {"now_cap_percent": "62.34 %", "height": "155.14", "capacity": "20,915.36", "time": "2011-05-11(7時)"}, "name": "翡翠水庫", "daily": {"capacity": "33,550.50", "end_time": "迄:2011-05-12(0時)", "nuclear": "--", "diff": "-0.26", "start_time": "起:2011-05-11(0時)", "in_water": "48.70", "rain": "0.00", "out_water": "240.50"}}, {"in_time": {"now_cap_percent": "40.69 %", "height": "135.53", "capacity": "217.70", "time": "2011-05-11(15時)"}, "name": "寶山水庫", "daily": {"capacity": "535.00", "end_time": "迄:2011-05-12(7時)", "nuclear": "--", "diff": "--", "start_time": "起:2011-05-11(7時)", "in_water": "2.36", "rain": "0.00", "out_water": "14.56"}}, {"in_time": {"now_cap_percent": "26.59 %", "height": "128.91", "capacity": "833.29", "time": "2011-05-11(17時)"}, "name": "寶山第二水庫", "daily": {"capacity": "3,134.00", "end_time": "迄:2011-05-12(0時)", "nuclear": "--", "diff": "--", "start_time": "起:2011-05-11(0時)", "in_water": "0.00", "rain": "0.00", "out_water": "15.41"}}, {"in_time": {"now_cap_percent": "35.38 %", "height": "71.59", "capacity": "994.10", "time": "2011-05-11(15時)"}, "name": "永和山水庫", "daily": {"capacity": "2,809.58", "end_time": "迄:2011-05-12(8時)", "nuclear": "--", "diff": "--", "start_time": "起:2011-05-11(8時)", "in_water": "3.10", "rain": "0.00", "out_water": "16.60"}}, {"in_time": {"now_cap_percent": "30.84 %", "height": "53.38", "capacity": "383.92", "time": "2011-05-11(9時)"}, "name": "明德水庫", "daily": {"capacity": "1,244.76", "end_time": "迄:2011-05-12(9時)", "nuclear": "--", "diff": "--", "start_time": "起:2011-05-11(9時)", "in_water": "2.70", "rain": "0.00", "out_water": "14.54"}}, {"in_time": {"now_cap_percent": "34.87 %", "height": "276.54", "capacity": "4,031.62", "time": "2011-05-11(23時)"}, "name": "鯉魚潭水庫", "daily": {"capacity": "11,562.00", "end_time": "迄:2011-05-12(0時)", "nuclear": "--", "diff": "--", "start_time": "起:2011-05-11(0時)", "in_water": "33.78", "rain": "--", "out_water": "73.53"}}, {"in_time": {"now_cap_percent": "53.34 %", "height": "1,387.00", "capacity": "8,112.71", "time": "2011-05-11(23時)"}, "name": "德基水庫", "daily": {"capacity": "15,209.61", "end_time": "迄:2011-05-12(0時)", "nuclear": "--", "diff": "--", "start_time": "起:2011-05-11(0時)", "in_water": "71.48", "rain": "0.00", "out_water": "148.17"}}, {"in_time": {"now_cap_percent": "13.93 %", "height": "271.02", "capacity": "26.48", "time": "2011-05-11(23時)"}, "name": "石岡壩", "daily": {"capacity": "190.12", "end_time": "迄:2011-05-12(0時)", "nuclear": "--", "diff": "--", "start_time": "起:2011-05-11(0時)", "in_water": "167.90", "rain": "0.00", "out_water": "166.40"}}, {"in_time": {"now_cap_percent": "--", "height": "--", "capacity": "--", "time": "--"}, "name": "霧社水庫", "daily": {"capacity": "--", "end_time": "迄:--", "nuclear": "--", "diff": "--", "start_time": "起:--", "in_water": "--", "rain": "--", "out_water": "--"}}, {"in_time": {"now_cap_percent": "--", "height": "--", "capacity": "--", "time": "--"}, "name": "日月潭水庫", "daily": {"capacity": "--", "end_time": "迄:--", "nuclear": "--", "diff": "--", "start_time": "起:--", "in_water": "--", "rain": "--", "out_water": "--"}}, {"in_time": {"now_cap_percent": "23.93 %", "height": "95.15", "capacity": "617.55", "time": "2011-05-11(8時)"}, "name": "仁義潭水庫", "daily": {"capacity": "2,580.61", "end_time": "迄:2011-05-12(8時)", "nuclear": "--", "diff": "--", "start_time": "起:2011-05-11(8時)", "in_water": "0.45", "rain": "0.00", "out_water": "13.77"}}, {"in_time": {"now_cap_percent": "21.13 %", "height": "64.01", "capacity": "195.64", "time": "2011-05-11(8時)"}, "name": "蘭潭水庫", "daily": {"capacity": "925.73", "end_time": "迄:2011-05-12(8時)", "nuclear": "--", "diff": "--", "start_time": "起:2011-05-11(8時)", "in_water": "4.09", "rain": "0.00", "out_water": "6.24"}}, {"in_time": {"now_cap_percent": "50.1 %", "height": "52.90", "capacity": "4,196.00", "time": "2011-05-11(7時)"}, "name": "烏山頭水庫", "daily": {"capacity": "8,375.00", "end_time": "迄:2011-05-12(7時)", "nuclear": "--", "diff": "--", "start_time": "起:2011-05-11(7時)", "in_water": "0.00", "rain": "0.00", "out_water": "134.10"}}, {"in_time": {"now_cap_percent": "9.21 %", "height": "188.62", "capacity": "4,527.00", "time": "2011-05-11(7時)"}, "name": "曾文水庫", "daily": {"capacity": "49,159.00", "end_time": "迄:2011-05-12(0時)", "nuclear": "--", "diff": "--", "start_time": "起:2011-05-11(0時)", "in_water": "6.00", "rain": "0.00", "out_water": "0.00"}}, {"in_time": {"now_cap_percent": "21.42 %", "height": "159.84", "capacity": "2,175.90", "time": "2011-05-11(7時)"}, "name": "南化水庫", "daily": {"capacity": "10,158.50", "end_time": "迄:2011-05-12(0時)", "nuclear": "--", "diff": "--", "start_time": "起:2011-05-11(0時)", "in_water": "1.40", "rain": "0.00", "out_water": "47.90"}}, {"in_time": {"now_cap_percent": "27.06 %", "height": "31.78", "capacity": "456.45", "time": "2011-05-11(7時)"}, "name": "阿公店水庫", "daily": {"capacity": "1,687.00", "end_time": "迄:2011-05-12(0時)", "nuclear": "--", "diff": "--", "start_time": "起:2011-05-11(0時)", "in_water": "0.14", "rain": "0.00", "out_water": "--"}}, {"in_time": {"now_cap_percent": "--", "height": "--", "capacity": "--", "time": "--"}, "name": "阿公店水庫(洩洪至二仁溪)", "daily": {"capacity": "--", "end_time": "迄:--", "nuclear": "--", "diff": "--", "start_time": "起:--", "in_water": "--", "rain": "--", "out_water": "--"}}, {"in_time": {"now_cap_percent": "48.42 %", "height": "129.11", "capacity": "1,352.39", "time": "2011-05-11(7時)"}, "name": "牡丹水庫", "daily": {"capacity": "2,793.04", "end_time": "迄:2011-05-12(0時)", "nuclear": "--", "diff": "--", "start_time": "起:2011-05-11(0時)", "in_water": "5.97", "rain": "0.00", "out_water": "9.50"}}, {"in_time": {"now_cap_percent": "5.58 %", "height": "3.21", "capacity": "5.80", "time": "2011-05-11(9時)"}, "name": "成功水庫", "daily": {"capacity": "104.00", "end_time": "迄:2011-05-12(0時)", "nuclear": "--", "diff": "2.00", "start_time": "起:2011-05-11(0時)", "in_water": "0.00", "rain": "0.00", "out_water": "0.15"}}]