[{"in_time": {"now_cap_percent": "86.65 %", "height": "241.67", "capacity": "18,108.25", "time": "2010-06-24(21時)"}, "name": "石門水庫", "daily": {"capacity": "20,898.00", "end_time": "迄:2010-06-25(0時)", "nuclear": "--", "diff": "--", "start_time": "起:2010-06-24(0時)", "in_water": "500.08", "rain": "15.10", "out_water": "274.58"}}, {"in_time": {"now_cap_percent": "98.89 %", "height": "82.80", "capacity": "818.80", "time": "2010-06-24(0時)"}, "name": "新山水庫", "daily": {"capacity": "828.00", "end_time": "迄:2010-06-25(0時)", "nuclear": "--", "diff": "--", "start_time": "起:2010-06-24(0時)", "in_water": "3.28", "rain": "20.50", "out_water": "10.64"}}, {"in_time": {"now_cap_percent": "64.79 %", "height": "155.96", "capacity": "21,782.80", "time": "2010-06-24(23時)"}, "name": "翡翠水庫", "daily": {"capacity": "33,621.65", "end_time": "迄:2010-06-25(0時)", "nuclear": "--", "diff": "--", "start_time": "起:2010-06-24(0時)", "in_water": "741.00", "rain": "39.20", "out_water": "225.46"}}, {"in_time": {"now_cap_percent": "64.45 %", "height": "138.31", "capacity": "344.80", "time": "2010-06-24(0時)"}, "name": "寶山水庫", "daily": {"capacity": "535.00", "end_time": "迄:2010-06-25(0時)", "nuclear": "--", "diff": "--", "start_time": "起:2010-06-24(0時)", "in_water": "3.23", "rain": "0.00", "out_water": "11.63"}}, {"in_time": {"now_cap_percent": "94.09 %", "height": "148.30", "capacity": "2,948.88", "time": "2010-06-24(0時)"}, "name": "寶山第二水庫", "daily": {"capacity": "3,134.00", "end_time": "迄:2010-06-25(0時)", "nuclear": "--", "diff": "--", "start_time": "起:2010-06-24(0時)", "in_water": "19.58", "rain": "0.00", "out_water": "13.12"}}, {"in_time": {"now_cap_percent": "94.74 %", "height": "84.14", "capacity": "2,661.90", "time": "2010-06-24(0時)"}, "name": "永和山水庫", "daily": {"capacity": "2,809.58", "end_time": "迄:2010-06-25(0時)", "nuclear": "--", "diff": "--", "start_time": "起:2010-06-24(0時)", "in_water": "48.40", "rain": "0.00", "out_water": "17.60"}}, {"in_time": {"now_cap_percent": "94.46 %", "height": "60.52", "capacity": "1,175.81", "time": "2010-06-24(0時)"}, "name": "明德水庫", "daily": {"capacity": "1,244.76", "end_time": "迄:2010-06-25(0時)", "nuclear": "--", "diff": "--", "start_time": "起:2010-06-24(0時)", "in_water": "12.72", "rain": "3.00", "out_water": "12.72"}}, {"in_time": {"now_cap_percent": "100 %", "height": "300.15", "capacity": "11,628.79", "time": "2010-06-24(16時)"}, "name": "鯉魚潭水庫", "daily": {"capacity": "11,562.00", "end_time": "迄:2010-06-25(0時)", "nuclear": "--", "diff": "--", "start_time": "起:2010-06-24(0時)", "in_water": "187.40", "rain": "8.71", "out_water": "92.88"}}, {"in_time": {"now_cap_percent": "--", "height": "1,399.54", "capacity": "12,263.57", "time": "2010-06-24(16時)"}, "name": "德基水庫", "daily": {"capacity": "--", "end_time": "迄:2010-06-25(0時)", "nuclear": "--", "diff": "--", "start_time": "起:2010-06-24(0時)", "in_water": "343.45", "rain": "0.50", "out_water": "743.59"}}, {"in_time": {"now_cap_percent": "13.34 %", "height": "271.48", "capacity": "25.37", "time": "2010-06-24(16時)"}, "name": "石岡壩", "daily": {"capacity": "190.12", "end_time": "迄:2010-06-25(0時)", "nuclear": "--", "diff": "--", "start_time": "起:2010-06-24(0時)", "in_water": "2,224.20", "rain": "6.00", "out_water": "2,226.50"}}, {"in_time": {"now_cap_percent": "--", "height": "--", "capacity": "--", "time": "--"}, "name": "霧社水庫", "daily": {"capacity": "--", "end_time": "迄:--", "nuclear": "--", "diff": "--", "start_time": "起:--", "in_water": "--", "rain": "--", "out_water": "--"}}, {"in_time": {"now_cap_percent": "--", "height": "--", "capacity": "--", "time": "--"}, "name": "日月潭水庫", "daily": {"capacity": "--", "end_time": "迄:--", "nuclear": "--", "diff": "--", "start_time": "起:--", "in_water": "--", "rain": "--", "out_water": "--"}}, {"in_time": {"now_cap_percent": "69.04 %", "height": "101.36", "capacity": "1,781.56", "time": "2010-06-24(0時)"}, "name": "仁義潭水庫", "daily": {"capacity": "2,580.61", "end_time": "迄:2010-06-25(0時)", "nuclear": "--", "diff": "--", "start_time": "起:2010-06-24(0時)", "in_water": "65.97", "rain": "17.50", "out_water": "48.99"}}, {"in_time": {"now_cap_percent": "72.67 %", "height": "72.01", "capacity": "672.74", "time": "2010-06-24(0時)"}, "name": "蘭潭水庫", "daily": {"capacity": "925.73", "end_time": "迄:2010-06-25(0時)", "nuclear": "--", "diff": "--", "start_time": "起:2010-06-24(0時)", "in_water": "39.50", "rain": "7.00", "out_water": "7.64"}}, {"in_time": {"now_cap_percent": "93.73 %", "height": "57.57", "capacity": "7,850.00", "time": "2010-06-24(0時)"}, "name": "烏山頭水庫", "daily": {"capacity": "8,375.00", "end_time": "迄:2010-06-25(0時)", "nuclear": "--", "diff": "--", "start_time": "起:2010-06-24(0時)", "in_water": "333.00", "rain": "51.30", "out_water": "222.00"}}, {"in_time": {"now_cap_percent": "36.77 %", "height": "205.72", "capacity": "18,074.00", "time": "2010-06-24(23時)"}, "name": "曾文水庫", "daily": {"capacity": "49,159.00", "end_time": "迄:2010-06-25(0時)", "nuclear": "--", "diff": "--", "start_time": "起:2010-06-24(0時)", "in_water": "276.60", "rain": "12.80", "out_water": "276.60"}}, {"in_time": {"now_cap_percent": "64.93 %", "height": "173.40", "capacity": "6,595.90", "time": "2010-06-24(0時)"}, "name": "南化水庫", "daily": {"capacity": "10,158.50", "end_time": "迄:2010-06-25(0時)", "nuclear": "--", "diff": "--", "start_time": "起:2010-06-24(0時)", "in_water": "243.60", "rain": "11.20", "out_water": "76.00"}}, {"in_time": {"now_cap_percent": "21.73 %", "height": "29.85", "capacity": "366.54", "time": "2010-06-24(23時)"}, "name": "阿公店水庫", "daily": {"capacity": "1,687.00", "end_time": "迄:2010-06-25(0時)", "nuclear": "--", "diff": "--", "start_time": "起:2010-06-24(0時)", "in_water": "5.66", "rain": "0.00", "out_water": "4.32"}}, {"in_time": {"now_cap_percent": "--", "height": "--", "capacity": "--", "time": "--"}, "name": "阿公店水庫(洩洪至二仁溪)", "daily": {"capacity": "--", "end_time": "迄:--", "nuclear": "--", "diff": "--", "start_time": "起:--", "in_water": "--", "rain": "--", "out_water": "--"}}, {"in_time": {"now_cap_percent": "48.04 %", "height": "128.99", "capacity": "1,341.70", "time": "2010-06-24(23時)"}, "name": "牡丹水庫", "daily": {"capacity": "2,793.04", "end_time": "迄:2010-06-25(0時)", "nuclear": "--", "diff": "--", "start_time": "起:2010-06-24(0時)", "in_water": "11.23", "rain": "0.00", "out_water": "11.23"}}, {"in_time": {"now_cap_percent": "25.05 %", "height": "5.19", "capacity": "26.05", "time": "2010-06-24(0時)"}, "name": "成功水庫", "daily": {"capacity": "104.00", "end_time": "迄:2010-06-25(0時)", "nuclear": "--", "diff": "--", "start_time": "起:2010-06-24(0時)", "in_water": "0.00", "rain": "0.00", "out_water": "0.21"}}]